setup.py
esputnixsnippets.egg-info/PKG-INFO
esputnixsnippets.egg-info/SOURCES.txt
esputnixsnippets.egg-info/dependency_links.txt
esputnixsnippets.egg-info/not-zip-safe
esputnixsnippets.egg-info/top_level.txt
snippets/__init__.py
snippets/generators.py