Metadata-Version: 1.0
Name: esputnixsnippets
Version: 0.1
Summary: The snippets joke in the world
Home-page: https://github.com/esputnix/snippets
Author: esputnix
Author-email: esputnix@gmail.com
License: MIT
Platform: UNKNOWN
